{"frames":{"000.png":{"frame":{"h":46,"idx":0,"w":45,"x":344,"y":466},"sourceSize":{"h":48,"w":47},"spriteSourceSize":{"x":1,"y":1}},"001.png":{"frame":{"h":82,"idx":0,"w":378,"x":0,"y":383},"sourceSize":{"h":82,"w":378},"spriteSourceSize":{"x":0,"y":0}},"002.png":{"frame":{"h":24,"idx":0,"w":31,"x":303,"y":497},"sourceSize":{"h":25,"w":32},"spriteSourceSize":{"x":0,"y":0}},"Game-incentive_bg.png":{"frame":{"h":87,"idx":0,"w":125,"x":457,"y":138},"sourceSize":{"h":94,"w":127},"spriteSourceSize":{"x":0,"y":4}},"ranking_line.png":{"frame":{"h":2,"idx":0,"w":10,"x":444,"y":214},"sourceSize":{"h":2,"w":10},"spriteSourceSize":{"x":0,"y":0}},"settlement_infor_bg.png":{"frame":{"h":36,"idx":0,"w":36,"x":503,"y":435},"sourceSize":{"h":36,"w":36},"spriteSourceSize":{"x":0,"y":0}},"settlement_infor_line.png":{"frame":{"h":112,"idx":0,"w":2,"x":390,"y":383},"sourceSize":{"h":120,"w":2},"spriteSourceSize":{"x":0,"y":4}},"settlement_infor_title_mask.png":{"frame":{"h":43,"idx":0,"w":44,"x":503,"y":391},"sourceSize":{"h":43,"w":44},"spriteSourceSize":{"x":0,"y":0}},"settlement_player_bg.png":{"frame":{"h":180,"idx":0,"w":223,"x":0,"y":68},"sourceSize":{"h":180,"w":223},"spriteSourceSize":{"x":0,"y":0}},"settlement_player_bg02.png":{"frame":{"h":164,"idx":0,"w":69,"x":503,"y":226},"sourceSize":{"h":164,"w":69},"spriteSourceSize":{"x":0,"y":0}},"settlement_player_goldbg.png":{"frame":{"h":40,"idx":0,"w":42,"x":390,"y":208},"sourceSize":{"h":40,"w":42},"spriteSourceSize":{"x":0,"y":0}},"settlement_player_light.png":{"frame":{"h":208,"idx":0,"w":98,"x":404,"y":315},"sourceSize":{"h":208,"w":98},"spriteSourceSize":{"x":0,"y":0}},"settlement_ranking_line.png":{"frame":{"h":2,"idx":0,"w":10,"x":433,"y":214},"sourceSize":{"h":2,"w":10},"spriteSourceSize":{"x":0,"y":0}},"settlement_title_challenge.png":{"frame":{"h":34,"idx":0,"w":114,"x":303,"y":524},"sourceSize":{"h":38,"w":114},"spriteSourceSize":{"x":0,"y":0}},"settlement_title_challenge_en.png":{"frame":{"h":67,"idx":0,"w":559,"x":0,"y":0},"sourceSize":{"h":72,"w":566},"spriteSourceSize":{"x":4,"y":3}},"settlement_title_defeated_en.png":{"frame":{"h":65,"idx":0,"w":483,"x":0,"y":249},"sourceSize":{"h":80,"w":490},"spriteSourceSize":{"x":5,"y":8}},"settlement_title_line.png":{"frame":{"h":2,"idx":0,"w":311,"x":0,"y":559},"sourceSize":{"h":2,"w":320},"spriteSourceSize":{"x":9,"y":0}},"settlement_title_victory_en.png":{"frame":{"h":67,"idx":0,"w":403,"x":0,"y":315},"sourceSize":{"h":80,"w":420},"spriteSourceSize":{"x":11,"y":7}},"settlement_txt_combo.png":{"frame":{"h":30,"idx":0,"w":197,"x":105,"y":497},"sourceSize":{"h":30,"w":197},"spriteSourceSize":{"x":0,"y":0}},"settlement_txt_get.png":{"frame":{"h":34,"idx":0,"w":109,"x":418,"y":524},"sourceSize":{"h":34,"w":109},"spriteSourceSize":{"x":0,"y":0}},"settlement_txt_lose.png":{"frame":{"h":69,"idx":0,"w":263,"x":224,"y":68},"sourceSize":{"h":69,"w":263},"spriteSourceSize":{"x":0,"y":0}},"settlement_txt_none.png":{"frame":{"h":10,"idx":0,"w":52,"x":433,"y":226},"sourceSize":{"h":16,"w":56},"spriteSourceSize":{"x":1,"y":4}},"settlement_txt_ranking.png":{"frame":{"h":30,"idx":0,"w":238,"x":105,"y":466},"sourceSize":{"h":30,"w":238},"spriteSourceSize":{"x":0,"y":0}},"settlement_txt_score.png":{"frame":{"h":38,"idx":0,"w":96,"x":488,"y":68},"sourceSize":{"h":38,"w":96},"spriteSourceSize":{"x":0,"y":0}},"settlement_txt_vs.png":{"frame":{"h":87,"idx":0,"w":104,"x":0,"y":466},"sourceSize":{"h":87,"w":104},"spriteSourceSize":{"x":0,"y":0}},"settlement_txt_win.png":{"frame":{"h":69,"idx":0,"w":232,"x":224,"y":138},"sourceSize":{"h":69,"w":232},"spriteSourceSize":{"x":0,"y":0}},"settlement_txt_winner.png":{"frame":{"h":36,"idx":0,"w":165,"x":224,"y":208},"sourceSize":{"h":36,"w":165},"spriteSourceSize":{"x":0,"y":0}},"textLine_01.png":{"frame":{"h":5,"idx":0,"w":14,"x":433,"y":208},"sourceSize":{"h":5,"w":14},"spriteSourceSize":{"x":0,"y":0}}},"meta":{"image":"Result_v20190806165337.png","prefix":"Atlas/Result/"}}
